pydevts/__init__.py
pydevts/conn.py
pydevts/errors.py
pydevts/node.py
pydevts/p2p.py
pydevts/routers/README.md
pydevts/routers/__init__.py
pydevts/routers/_base.py
pydevts/routers/basic.py
pydevts/routers/hopbased.py
pydevts-0.1.1.dist-info/WHEEL
pydevts-0.1.1.dist-info/METADATA
pydevts-0.1.1.dist-info/RECORD
