Metadata-Version: 2.1
Name: pydevts
Version: 0.1.1
Summary: PYDEVTS (PYthon Distributed EVenT System) is a distributed event system written in python and based on the concept of nodes that is designed for the implementation of data stores and other replicated systems.
Home-page: https://github.com/Peperworx/pydevts
Author: Riley Wilton
Author-email: meetingprince34@outlook.com
Requires-Python: >=3.9,<4.0
Classifier: Programming Language :: Python :: 3
Classifier: Programming Language :: Python :: 3.9
Requires-Dist: anyio (>=3.1.0,<4.0.0)
Requires-Dist: msgpack (>=1.0.2,<2.0.0)
Requires-Dist: networkx (>=2.5.1,<3.0.0)
Project-URL: Repository, https://github.com/Peperworx/pydevts
